ethermine_monitor/__init__.py
ethermine_monitor/app.py
ethermine_monitor/email.py
ethermine_monitor-1.0.0.dist-info/DESCRIPTION.rst
ethermine_monitor-1.0.0.dist-info/METADATA
ethermine_monitor-1.0.0.dist-info/RECORD
ethermine_monitor-1.0.0.dist-info/WHEEL
ethermine_monitor-1.0.0.dist-info/metadata.json
ethermine_monitor-1.0.0.dist-info/top_level.txt
ethermine_monitor-1.0.0.dist-info/zip-safe
tests/__init__.py
tests/test_app.py
