Metadata-Version: 2.0
Name: ethermine-monitor
Version: 1.0.0
Summary: Monitor ethermine workers
Home-page: https://github.com/narfman0/ethermine-monitor
Author: Jon Robison
Author-email: narfman0@gmail.com
License: LICENSE
Keywords: bot monitor crypto cryptocurrency ethermine
Platform: UNKNOWN
Classifier: Development Status :: 4 - Beta
Classifier: License :: OSI Approved :: GNU General Public License v3 (GPLv3)
Classifier: Operating System :: OS Independent
Classifier: Programming Language :: Python
Classifier: Topic :: Software Development :: Libraries :: Python Modules
Requires-Dist: flask
Requires-Dist: requests
